verbosify/__init__.py
verbosify/rewrite_source_code.py
verbosify/verbosify.py
verbosify-0.0.1.dist-info/LICENSE
verbosify-0.0.1.dist-info/METADATA
verbosify-0.0.1.dist-info/WHEEL
verbosify-0.0.1.dist-info/top_level.txt
verbosify-0.0.1.dist-info/RECORD
