Metadata-Version: 2.1
Name: verbosify
Version: 0.0.1
Summary: A cool python function decorator to print comments
Home-page: https://github.com/rhuille/verbosify
Author: Raphael Huille
Author-email: raphael.huille@gmail.com
License: MIT
Platform: UNKNOWN
Requires-Python: >=3.8
